ansible_lint_junit/__init__.py
ansible_lint_junit/main.py
ansible_lint_junit/version.py
ansible_lint_junit-0.17.8.dist-info/LICENSE.txt
ansible_lint_junit-0.17.8.dist-info/METADATA
ansible_lint_junit-0.17.8.dist-info/WHEEL
ansible_lint_junit-0.17.8.dist-info/entry_points.txt
ansible_lint_junit-0.17.8.dist-info/top_level.txt
ansible_lint_junit-0.17.8.dist-info/RECORD
