Metadata-Version: 2.1
Name: ansible-lint-junit
Version: 0.17.8
Summary: ansible-lint to JUnit converter.
Home-page: https://github.com/wasilak/ansible-lint-junit
Download-URL: https://github.com/wasilak/ansible-lint-junit/archive/0.17.8.tar.gz
Author: wasil
Author-email: piotr.m.boruc@gmail.com
Keywords: ansible,junit
Classifier: Programming Language :: Python :: 3
Classifier: License :: OSI Approved :: MIT License
Classifier: Operating System :: OS Independent
Requires-Python: >=3.6
License-File: LICENSE.txt
Requires-Dist: ansible-lint >=5.0.7
Requires-Dist: defusedxml >=0.7.1
